[
  {
    "applicationdate": "02-11-2020",
    "applicationnumber": "880412109183615001",
    "applicationstatus": "Rejected",
    "approvalcomments": "Incorrect Address",
    "fanidnumber": "33629236",
    "documenttype": "QID",
    "documentnumber": "3154234",
    "nationality": "Qatar",
    "firstname": "Razi",
    "lastname": "Ibrahim",
    "mobilenumber": "+20 891241356",
    "gender": "Male",
    "dateofbirth": "03-06-1994",
    "profession": "Designer",
    "salary": "EGP 20000",
    "submissiontype": "Bulk Registration Upload",
    "fanidcarddetails": "Printed"
  },
  {
    "applicationdate": "02-11-2020",
    "applicationnumber": "880412109183615003",
    "applicationstatus": "Under Review",
    "approvalcomments": "Visa details not available",
    "fanidnumber": "43629231",
    "documenttype": "Passport",
    "documentnumber": "2154554",
    "nationality": "Egypt",
    "firstname": "Mohammed",
    "lastname": "Ibrahim",
    "mobilenumber": "+20 891241356",
    "gender": "Male",
    "dateofbirth": "03-06-1994",
    "profession": "Designer",
    "salary": "EGP 20000",
    "submissiontype": "Bulk Registration Upload",
    "fanidcarddetails": "Printed"
  },
  {
    "applicationdate": "02-11-2020",
    "applicationnumber": "100412109183621235",
    "applicationstatus": "Approved",
    "approvalcomments": "",
    "fanidnumber": "43629232",
    "documenttype": "QID",
    "documentnumber": "0154550",
    "nationality": "Qatar",
    "firstname": "Ibrahim",
    "lastname": "Ibrahim",
    "mobilenumber": "+20 891241356",
    "gender": "Male",
    "dateofbirth": "03-06-1994",
    "profession": "Designer",
    "salary": "EGP 20000",
    "submissiontype": "Bulk Registration Upload",
    "fanidcarddetails": "Printed"
  },
  {
    "applicationdate": "02-11-2020",
    "applicationnumber": "100412109183621236",
    "applicationstatus": "*Need More Info",
    "approvalcomments": "Visa details not available",
    "fanidnumber": "43629233",
    "documenttype": "Passport",
    "documentnumber": "3154234",
    "nationality": "Egypt",
    "firstname": "Rizwan",
    "lastname": "Ibrahim",
    "mobilenumber": "+20 891241356",
    "gender": "Male",
    "dateofbirth": "03-06-1994",
    "profession": "Designer",
    "salary": "EGP 20000",
    "submissiontype": "Bulk Registration Upload",
    "fanidcarddetails": "Printed"
  },
  {
    "applicationdate": "02-11-2020",
    "applicationnumber": "100412109183621237",
    "applicationstatus": "*Need More Info",
    "approvalcomments": "",
    "fanidnumber": "43629234",
    "documenttype": "QID",
    "documentnumber": "4154523",
    "nationality": "Qatar",
    "firstname": "Mohammed",
    "lastname": "Ibrahim",
    "mobilenumber": "+20 891241356",
    "gender": "Male",
    "dateofbirth": "03-06-1994",
    "profession": "Designer",
    "salary": "EGP 20000",
    "submissiontype": "Bulk Registration Upload",
    "fanidcarddetails": "Printed"
  },
  {
    "applicationdate": "02-11-2020",
    "applicationnumber": "100412109183621238",
    "applicationstatus": "*Need More Info",
    "approvalcomments": "Visa details not available",
    "fanidnumber": "43629235",
    "documenttype": "Passport",
    "documentnumber": "1154551",
    "nationality": "Egypt",
    "firstname": "Mohammed",
    "lastname": "Ibrahim",
    "mobilenumber": "+20 891241356",
    "gender": "Male",
    "dateofbirth": "03-06-1994",
    "profession": "Designer",
    "salary": "EGP 20000",
    "submissiontype": "Bulk Registration Upload",
    "fanidcarddetails": "Printed"
  },
  {
    "applicationdate": "02-11-2020",
    "applicationnumber": "100412109183621239",
    "applicationstatus": "*Need More Info",
    "approvalcomments": "Incorrect Address",
    "fanidnumber": "43629236",
    "documenttype": "QID",
    "documentnumber": "3154234",
    "nationality": "Qatar",
    "firstname": "Mohammed",
    "lastname": "Faizal",
    "mobilenumber": "+20 891241356",
    "gender": "Male",
    "dateofbirth": "03-06-1994",
    "profession": "Designer",
    "salary": "EGP 20000",
    "submissiontype": "Bulk Registration Upload",
    "fanidcarddetails": "Printed"
  },
  {
    "applicationdate": "02-11-2020",
    "applicationnumber": "100412109183621240",
    "applicationstatus": "*Need More Info",
    "approvalcomments": "Incorrect Address",
    "fanidnumber": "43629237",
    "documenttype": "QID",
    "documentnumber": "3154234",
    "nationality": "Qatar",
    "firstname": "Faizal",
    "lastname": "Nihal",
    "mobilenumber": "+20 891241356",
    "gender": "Male",
    "dateofbirth": "03-06-1994",
    "profession": "Designer",
    "salary": "EGP 20000",
    "submissiontype": "Bulk Registration Upload",
    "fanidcarddetails": "Printed"
  },
  {
    "applicationdate": "02-11-2020",
    "applicationnumber": "100412109183621256",
    "applicationstatus": "*Need More Info",
    "approvalcomments": "Incorrect Address",
    "fanidnumber": "43629238",
    "documenttype": "QID",
    "documentnumber": "3154234",
    "nationality": "Qatar",
    "firstname": "Faizal",
    "lastname": "Nihal",
    "mobilenumber": "+20 891241356",
    "gender": "Male",
    "dateofbirth": "03-06-1994",
    "profession": "Designer",
    "salary": "EGP 20000",
    "submissiontype": "Bulk Registration Upload",
    "fanidcarddetails": "Printed"
  },
  {
    "applicationdate": "02-11-2020",
    "applicationnumber": "880412109183615012",
    "applicationstatus": "*Need More Info",
    "approvalcomments": "",
    "fanidnumber": "43629239",
    "documenttype": "QID",
    "documentnumber": "3154234",
    "nationality": "Qatar",
    "firstname": "Faizal",
    "lastname": "Nihal",
    "mobilenumber": "+20 891241356",
    "gender": "Male",
    "dateofbirth": "03-06-1994",
    "profession": "Designer",
    "salary": "EGP 20000",
    "submissiontype": "Bulk Registration Upload",
    "fanidcarddetails": "Printed"
  },
  {
    "applicationdate": "02-11-2020",
    "applicationnumber": "880412109183615013",
    "applicationstatus": "*Need More Info",
    "approvalcomments": "",
    "fanidnumber": "00629230",
    "documenttype": "QID",
    "documentnumber": "3154234",
    "nationality": "Qatar",
    "firstname": "Faizal",
    "lastname": "Nihal",
    "mobilenumber": "+20 891241356",
    "gender": "Male",
    "dateofbirth": "03-06-1994",
    "profession": "Designer",
    "salary": "EGP 20000",
    "submissiontype": "Bulk Registration Upload",
    "fanidcarddetails": "Printed"
  },
  {
    "applicationdate": "02-11-2020",
    "applicationnumber": "880412109183615001",
    "applicationstatus": "*Need More Info",
    "approvalcomments": "",
    "fanidnumber": "00629231",
    "documenttype": "QID",
    "documentnumber": "3154234",
    "nationality": "Qatar",
    "firstname": "Faizal",
    "lastname": "Nihal",
    "mobilenumber": "+20 891241356",
    "gender": "Male",
    "dateofbirth": "03-06-1994",
    "profession": "Designer",
    "salary": "EGP 20000",
    "submissiontype": "Bulk Registration Upload",
    "fanidcarddetails": "Printed"
  },
  {
    "applicationdate": "02-11-2020",
    "applicationnumber": "880412109183615025",
    "applicationstatus": "*Need More Info",
    "approvalcomments": "",
    "fanidnumber": "00629232",
    "documenttype": "QID",
    "documentnumber": "0154550",
    "nationality": "Qatar",
    "firstname": "Faizal",
    "lastname": "Nihal",
    "mobilenumber": "+20 891241356",
    "gender": "Male",
    "dateofbirth": "03-06-1994",
    "profession": "Designer",
    "salary": "EGP 20000",
    "submissiontype": "Bulk Registration Upload",
    "fanidcarddetails": "Printed"
  },
  {
    "applicationdate": "02-11-2020",
    "applicationnumber": "100412109183621234",
    "applicationstatus": "*Need More Info",
    "approvalcomments": "",
    "fanidnumber": "00629233",
    "documenttype": "Passport",
    "documentnumber": "0154550",
    "nationality": "Egypt",
    "firstname": "Mohammed",
    "lastname": "Nihal",
    "mobilenumber": "+20 891241356",
    "gender": "Male",
    "dateofbirth": "03-06-1994",
    "profession": "Designer",
    "salary": "EGP 20000",
    "submissiontype": "Bulk Registration Upload",
    "fanidcarddetails": "Printed"
  },
  {
    "applicationdate": "02-11-2020",
    "applicationnumber": "100412109183621235",
    "applicationstatus": "*Need More Info",
    "approvalcomments": "",
    "fanidnumber": "00629234",
    "documenttype": "Passport",
    "documentnumber": "0154550",
    "nationality": "Egypt",
    "firstname": "Mohammed",
    "lastname": "Nihal",
    "mobilenumber": "+20 891241356",
    "gender": "Male",
    "dateofbirth": "03-06-1994",
    "profession": "Designer",
    "salary": "EGP 20000",
    "submissiontype": "Bulk Registration Upload",
    "fanidcarddetails": "Printed"
  },
  {
    "applicationdate": "02-11-2020",
    "applicationnumber": "100412109183621236",
    "applicationstatus": "Under Review",
    "approvalcomments": "",
    "fanidnumber": "00629235",
    "documenttype": "Passport",
    "documentnumber": "0154550",
    "nationality": "Egypt",
    "firstname": "Mohammed",
    "lastname": "Faizal",
    "mobilenumber": "+20 891241356",
    "gender": "Male",
    "dateofbirth": "03-06-1994",
    "profession": "Designer",
    "salary": "EGP 20000",
    "submissiontype": "Bulk Registration Upload",
    "fanidcarddetails": "Printed"
  },
  {
    "applicationdate": "02-11-2020",
    "applicationnumber": "100412109183621237",
    "applicationstatus": "Under Review",
    "approvalcomments": "",
    "fanidnumber": "00629236",
    "documenttype": "Passport",
    "documentnumber": "4154523",
    "nationality": "Egypt",
    "firstname": "Mohammed",
    "lastname": "Ahmed",
    "mobilenumber": "+20 891241356",
    "gender": "Male",
    "dateofbirth": "03-06-1994",
    "profession": "Designer",
    "salary": "EGP 20000",
    "submissiontype": "Bulk Registration Upload",
    "fanidcarddetails": "Printed"
  },
  {
    "applicationdate": "02-11-2020",
    "applicationnumber": "100412109183625363",
    "applicationstatus": "Under Review",
    "approvalcomments": "",
    "fanidnumber": "00629237",
    "documenttype": "Passport",
    "documentnumber": "1154551",
    "nationality": "Egypt",
    "firstname": "Rizwan",
    "lastname": "Ahmed",
    "mobilenumber": "+20 891241356",
    "gender": "Male",
    "dateofbirth": "03-06-1994",
    "profession": "Designer",
    "salary": "EGP 20000",
    "submissiontype": "Bulk Registration Upload",
    "fanidcarddetails": "Printed"
  },
  {
    "applicationdate": "02-11-2020",
    "applicationnumber": "100412109183625317",
    "applicationstatus": "Under Review",
    "approvalcomments": "Visa details not available",
    "fanidnumber": "52629239",
    "documenttype": "Passport",
    "documentnumber": "4154523",
    "nationality": "Egypt",
    "firstname": "Rizwan",
    "lastname": "Ahmed",
    "mobilenumber": "+20 891241356",
    "gender": "Male",
    "dateofbirth": "03-06-1994",
    "profession": "Designer",
    "salary": "EGP 20000",
    "submissiontype": "Bulk Registration Upload",
    "fanidcarddetails": "Printed"
  },
  {
    "applicationdate": "02-11-2020",
    "applicationnumber": "100412109183625369",
    "applicationstatus": "Under Review",
    "approvalcomments": "Visa details not available",
    "fanidnumber": "52629238",
    "documenttype": "Passport",
    "documentnumber": "1154551",
    "nationality": "Egypt",
    "firstname": "Rizwan",
    "lastname": "Ahmed",
    "mobilenumber": "+20 891241356",
    "gender": "Male",
    "dateofbirth": "03-06-1994",
    "profession": "Designer",
    "salary": "EGP 20000",
    "submissiontype": "Bulk Registration Upload",
    "fanidcarddetails": "Printed"
  },
  {
    "applicationdate": "02-11-2020",
    "applicationnumber": "100412109183625362",
    "applicationstatus": "Under Review",
    "approvalcomments": "Visa details not available",
    "fanidnumber": "52629230",
    "documenttype": "Passport",
    "documentnumber": "1154551",
    "nationality": "Egypt",
    "firstname": "Rizwan",
    "lastname": "Ahmed",
    "mobilenumber": "+20 891241356",
    "gender": "Male",
    "dateofbirth": "03-06-1994",
    "profession": "Designer",
    "salary": "EGP 20000",
    "submissiontype": "Bulk Registration Upload",
    "fanidcarddetails": "Printed"
  },
  {
    "applicationdate": "02-11-2020",
    "applicationnumber": "100412109183625366",
    "applicationstatus": "Under Review",
    "approvalcomments": "Visa details not available",
    "fanidnumber": "52629231",
    "documenttype": "Passport",
    "documentnumber": "1154551",
    "nationality": "Egypt",
    "firstname": "Rizwan",
    "lastname": "Ahmed",
    "mobilenumber": "+20 891241356",
    "gender": "Male",
    "dateofbirth": "03-06-1994",
    "profession": "Designer",
    "salary": "EGP 20000",
    "submissiontype": "Bulk Registration Upload",
    "fanidcarddetails": "Printed"
  },
  {
    "applicationdate": "02-11-2020",
    "applicationnumber": "100412109183625367",
    "applicationstatus": "Approved",
    "approvalcomments": "Visa details not available",
    "fanidnumber": "52629232",
    "documenttype": "Passport",
    "documentnumber": "4154523",
    "nationality": "Egypt",
    "firstname": "Rizwan",
    "lastname": "Ahmed",
    "mobilenumber": "+20 891241356",
    "gender": "Male",
    "dateofbirth": "03-06-1994",
    "profession": "Designer",
    "salary": "EGP 20000",
    "submissiontype": "Bulk Registration Upload",
    "fanidcarddetails": "Printed"
  },
  {
    "applicationdate": "02-11-2020",
    "applicationnumber": "100412109183627659",
    "applicationstatus": "Approved",
    "approvalcomments": "Visa details not available",
    "fanidnumber": "12629233",
    "documenttype": "Passport",
    "documentnumber": "1154551",
    "nationality": "Egypt",
    "firstname": "Rizwan",
    "lastname": "Ahmed",
    "mobilenumber": "+20 891241356",
    "gender": "Male",
    "dateofbirth": "03-06-1994",
    "profession": "Designer",
    "salary": "EGP 20000",
    "submissiontype": "Bulk Registration Upload",
    "fanidcarddetails": "Printed"
  },
  {
    "applicationdate": "02-11-2020",
    "applicationnumber": "100412109183627650",
    "applicationstatus": "Approved",
    "approvalcomments": "Visa details not available",
    "fanidnumber": "12629234",
    "documenttype": "Passport",
    "documentnumber": "4154523",
    "nationality": "Egypt",
    "firstname": "Rizwan",
    "lastname": "Faizal",
    "mobilenumber": "+20 891241356",
    "gender": "Male",
    "dateofbirth": "03-06-1994",
    "profession": "Designer",
    "salary": "EGP 20000",
    "submissiontype": "Bulk Registration Upload",
    "fanidcarddetails": "Printed"
  },
  {
    "applicationdate": "02-11-2020",
    "applicationnumber": "100412109183627651",
    "applicationstatus": "Approved",
    "approvalcomments": "Visa details not available",
    "fanidnumber": "33629231",
    "documenttype": "Passport",
    "documentnumber": "1154551",
    "nationality": "Egypt",
    "firstname": "Rizwan",
    "lastname": "Faizal",
    "mobilenumber": "+20 891241356",
    "gender": "Male",
    "dateofbirth": "03-06-1994",
    "profession": "Designer",
    "salary": "EGP 20000",
    "submissiontype": "Bulk Registration Upload",
    "fanidcarddetails": "Printed"
  },
  {
    "applicationdate": "02-11-2020",
    "applicationnumber": "100412109183627652",
    "applicationstatus": "Approved",
    "approvalcomments": "Incorrect Address",
    "fanidnumber": "33629230",
    "documenttype": "Passport",
    "documentnumber": "4154523",
    "nationality": "Egypt",
    "firstname": "Mohammed",
    "lastname": "Faizal",
    "mobilenumber": "+20 891241356",
    "gender": "Male",
    "dateofbirth": "03-06-1994",
    "profession": "Designer",
    "salary": "EGP 20000",
    "submissiontype": "Bulk Registration Upload",
    "fanidcarddetails": "Printed"
  },
  {
    "applicationdate": "02-11-2020",
    "applicationnumber": "100412109183627653",
    "applicationstatus": "Approved",
    "approvalcomments": "Incorrect Address",
    "fanidnumber": "33629233",
    "documenttype": "Passport",
    "documentnumber": "4154523",
    "nationality": "Egypt",
    "firstname": "Mohammed",
    "lastname": "Faizal",
    "mobilenumber": "+20 891241356",
    "gender": "Male",
    "dateofbirth": "03-06-1994",
    "profession": "Designer",
    "salary": "EGP 20000",
    "submissiontype": "Bulk Registration Upload",
    "fanidcarddetails": "Printed"
  },
  {
    "applicationdate": "02-11-2020",
    "applicationnumber": "100412109183627654",
    "applicationstatus": "Approved",
    "approvalcomments": "Incorrect Address",
    "fanidnumber": "33629235",
    "documenttype": "Passport",
    "documentnumber": "1154551",
    "nationality": "Egypt",
    "firstname": "Mohammed",
    "lastname": "Faizal",
    "mobilenumber": "+20 891241356",
    "gender": "Male",
    "dateofbirth": "03-06-1994",
    "profession": "Designer",
    "salary": "EGP 20000",
    "submissiontype": "Bulk Registration Upload",
    "fanidcarddetails": "Printed"
  },
  {
    "applicationdate": "02-11-2020",
    "applicationnumber": "100412109183627655",
    "applicationstatus": "Approved",
    "approvalcomments": "Incorrect Address",
    "fanidnumber": "33629239",
    "documenttype": "Passport",
    "documentnumber": "4154523",
    "nationality": "Egypt",
    "firstname": "Mohammed",
    "lastname": "Faizal",
    "mobilenumber": "+20 891241356",
    "gender": "Male",
    "dateofbirth": "03-06-1994",
    "profession": "Designer",
    "salary": "EGP 20000",
    "submissiontype": "Bulk Registration Upload",
    "fanidcarddetails": "Printed"
  },
  {
    "applicationdate": "02-11-2020",
    "applicationnumber": "100412109183627656",
    "applicationstatus": "Rejected",
    "approvalcomments": "Incorrect Address",
    "fanidnumber": "33629223",
    "documenttype": "Passport",
    "documentnumber": "1154551",
    "nationality": "Egypt",
    "firstname": "Mohammed",
    "lastname": "Faizal",
    "mobilenumber": "+20 891241356",
    "gender": "Male",
    "dateofbirth": "03-06-1994",
    "profession": "Designer",
    "salary": "EGP 20000",
    "submissiontype": "Bulk Registration Upload",
    "fanidcarddetails": "Printed"
  },
  {
    "applicationdate": "02-11-2020",
    "applicationnumber": "100412109183627657",
    "applicationstatus": "Rejected",
    "approvalcomments": "Incorrect Address",
    "fanidnumber": "33629243",
    "documenttype": "Passport",
    "documentnumber": "2154554",
    "nationality": "Egypt",
    "firstname": "Mohammed",
    "lastname": "Faizal",
    "mobilenumber": "+20 891241356",
    "gender": "Male",
    "dateofbirth": "03-06-1994",
    "profession": "Designer",
    "salary": "EGP 20000",
    "submissiontype": "Bulk Registration Upload",
    "fanidcarddetails": "Printed"
  }
]
